[
  {
    "species_id": "porthidium_lansbergii",
    "taxon_id": 31014,
    "rank": "species",
    "matched_name": "Porthidium lansbergii",
    "exact_match": true
  },
  {
    "species_id": "pseudocerastes_fieldi",
    "taxon_id": 30993,
    "rank": "species",
    "matched_name": "Pseudocerastes fieldi",
    "exact_match": true
  },
  {
    "species_id": "trimeresurus_gumprechti",
    "taxon_id": 30976,
    "rank": "species",
    "matched_name": "Trimeresurus gumprechti",
    "exact_match": true
  },
  {
    "species_id": "trimeresurus_insularis",
    "taxon_id": 146509,
    "rank": "species",
    "matched_name": "Trimeresurus insularis",
    "exact_match": true
  },
  {
    "species_id": "trimeresurus_sumatranus",
    "taxon_id": 146513,
    "rank": "species",
    "matched_name": "Trimeresurus sumatranus",
    "exact_match": true
  },
  {
    "species_id": "ovophis_monticola",
    "taxon_id": 31024,
    "rank": "species",
    "matched_name": "Ovophis monticola",
    "exact_match": true
  },
  {
    "species_id": "trimeresurus_vogeli",
    "taxon_id": 30947,
    "rank": "species",
    "matched_name": "Trimeresurus vogeli",
    "exact_match": true
  },
  {
    "species_id": "vipera_dinniki",
    "taxon_id": 73996,
    "rank": "species",
    "matched_name": "Vipera dinniki",
    "exact_match": true
  },
  {
    "species_id": "montivipera_latifii",
    "taxon_id": 30920,
    "rank": "species",
    "matched_name": "Montivipera latifii",
    "exact_match": true
  },
  {
    "species_id": "ophryacus_smaragdinus",
    "taxon_id": 540011,
    "rank": "species",
    "matched_name": "Ophryacus smaragdinus",
    "exact_match": true
  }
]