{
  "timestamp": 1755944223586,
  "data": {
    "batchcomplete": "",
    "warnings": {
      "query": {
        "*": "Unrecognized value for parameter \"prop\": extmetadata"
      }
    },
    "query": {
      "pages": {
        "45754305": {
          "pageid": 45754305,
          "ns": 6,
          "title": "File:Agkistrodon contortrix02.jpg",
          "imagerepository": "local",
          "imageinfo": [
            {
              "size": 75440,
              "width": 528,
              "height": 960,
              "url": "https://upload.wikimedia.org/wikipedia/commons/f/f2/Agkistrodon_contortrix02.jpg",
              "descriptionurl": "https://commons.wikimedia.org/wiki/File:Agkistrodon_contortrix02.jpg",
              "descriptionshorturl": "https://commons.wikimedia.org/w/index.php?curid=45754305"
            }
          ]
        }
      }
    }
  }
}