{
  "timestamp": 1755944182464,
  "data": {
    "batchcomplete": "",
    "warnings": {
      "query": {
        "*": "Unrecognized value for parameter \"prop\": extmetadata"
      }
    },
    "query": {
      "pages": {
        "117658707": {
          "pageid": 117658707,
          "ns": 6,
          "title": "File:Crotalus ruber 63293275.jpg",
          "imagerepository": "local",
          "imageinfo": [
            {
              "size": 1409651,
              "width": 2048,
              "height": 1365,
              "url": "https://upload.wikimedia.org/wikipedia/commons/f/fc/Crotalus_ruber_63293275.jpg",
              "descriptionurl": "https://commons.wikimedia.org/wiki/File:Crotalus_ruber_63293275.jpg",
              "descriptionshorturl": "https://commons.wikimedia.org/w/index.php?curid=117658707"
            }
          ]
        }
      }
    }
  }
}