{
  "timestamp": 1755947181102,
  "data": {
    "batchcomplete": "",
    "warnings": {
      "query": {
        "*": "Unrecognized value for parameter \"prop\": extmetadata"
      }
    },
    "query": {
      "pages": {
        "117656235": {
          "pageid": 117656235,
          "ns": 6,
          "title": "File:Crotalus adamanteus 115783973.jpg",
          "imagerepository": "local",
          "imageinfo": [
            {
              "size": 590121,
              "width": 2048,
              "height": 1366,
              "url": "https://upload.wikimedia.org/wikipedia/commons/9/95/Crotalus_adamanteus_115783973.jpg",
              "descriptionurl": "https://commons.wikimedia.org/wiki/File:Crotalus_adamanteus_115783973.jpg",
              "descriptionshorturl": "https://commons.wikimedia.org/w/index.php?curid=117656235"
            }
          ]
        }
      }
    }
  }
}