{
  "timestamp": 1755945398297,
  "data": {
    "batchcomplete": "",
    "warnings": {
      "query": {
        "*": "Unrecognized value for parameter \"prop\": extmetadata"
      }
    },
    "query": {
      "pages": {
        "93341532": {
          "pageid": 93341532,
          "ns": 6,
          "title": "File:Catalogue of the osteological portion of specimens contained in the Anatomical Museum of the University of Cambridge (IA b24756295).pdf",
          "imagerepository": "local",
          "imageinfo": [
            {
              "size": 6559739,
              "width": 1100,
              "height": 1760,
              "pagecount": 148,
              "url": "https://upload.wikimedia.org/wikipedia/commons/1/15/Catalogue_of_the_osteological_portion_of_specimens_contained_in_the_Anatomical_Museum_of_the_University_of_Cambridge_%28IA_b24756295%29.pdf",
              "descriptionurl": "https://commons.wikimedia.org/wiki/File:Catalogue_of_the_osteological_portion_of_specimens_contained_in_the_Anatomical_Museum_of_the_University_of_Cambridge_(IA_b24756295).pdf",
              "descriptionshorturl": "https://commons.wikimedia.org/w/index.php?curid=93341532"
            }
          ]
        }
      }
    }
  }
}