{
  "timestamp": 1755943759233,
  "data": {
    "batchcomplete": "",
    "warnings": {
      "query": {
        "*": "Unrecognized value for parameter \"prop\": extmetadata"
      }
    },
    "query": {
      "pages": {
        "58424599": {
          "pageid": 58424599,
          "ns": 6,
          "title": "File:Vipera berus 221.jpg",
          "imagerepository": "local",
          "imageinfo": [
            {
              "size": 206348,
              "width": 1100,
              "height": 636,
              "url": "https://upload.wikimedia.org/wikipedia/commons/1/1c/Vipera_berus_221.jpg",
              "descriptionurl": "https://commons.wikimedia.org/wiki/File:Vipera_berus_221.jpg",
              "descriptionshorturl": "https://commons.wikimedia.org/w/index.php?curid=58424599"
            }
          ]
        }
      }
    }
  }
}