{
  "timestamp": 1755944692903,
  "data": {
    "batchcomplete": "",
    "warnings": {
      "query": {
        "*": "Unrecognized value for parameter \"prop\": extmetadata"
      }
    },
    "query": {
      "pages": {
        "91458833": {
          "pageid": 91458833,
          "ns": 6,
          "title": "File:The animal kingdom, arranged according to its organization, serving as a foundation for the natural history of animals - and an introduction to comparative anatomy (IA animalkingdomarr02cuvier).pdf",
          "imagerepository": "local",
          "imageinfo": [
            {
              "size": 22787460,
              "width": 712,
              "height": 1239,
              "pagecount": 454,
              "url": "https://upload.wikimedia.org/wikipedia/commons/4/40/The_animal_kingdom%2C_arranged_according_to_its_organization%2C_serving_as_a_foundation_for_the_natural_history_of_animals_-_and_an_introduction_to_comparative_anatomy_%28IA_animalkingdomarr02cuvier%29.pdf",
              "descriptionurl": "https://commons.wikimedia.org/wiki/File:The_animal_kingdom,_arranged_according_to_its_organization,_serving_as_a_foundation_for_the_natural_history_of_animals_-_and_an_introduction_to_comparative_anatomy_(IA_animalkingdomarr02cuvier).pdf",
              "descriptionshorturl": "https://commons.wikimedia.org/w/index.php?curid=91458833"
            }
          ]
        }
      }
    }
  }
}