{
  "timestamp": 1755986366793,
  "data": {
    "total_results": 1,
    "page": 1,
    "per_page": 10,
    "results": [
      {
        "id": 30965,
        "rank": "species",
        "rank_level": 10,
        "iconic_taxon_id": 26036,
        "ancestor_ids": [
          48460,
          1,
          2,
          355675,
          26036,
          26172,
          85553,
          30667,
          797576,
          30941,
          30965
        ],
        "is_active": true,
        "name": "Trimeresurus kanburiensis",
        "parent_id": 30941,
        "ancestry": "48460/1/2/355675/26036/26172/85553/30667/797576/30941",
        "extinct": false,
        "default_photo": {
          "id": 91245453,
          "license_code": "cc-by-nc",
          "attribution": "(c) Siriwat Dangsri, some rights reserved (CC BY-NC), uploaded by Siriwat Dangsri",
          "url": "https://inaturalist-open-data.s3.amazonaws.com/photos/91245453/square.jpeg",
          "original_dimensions": {
            "height": 1536,
            "width": 2048
          },
          "flags": [],
          "attribution_name": "Siriwat Dangsri",
          "square_url": "https://inaturalist-open-data.s3.amazonaws.com/photos/91245453/square.jpeg",
          "medium_url": "https://inaturalist-open-data.s3.amazonaws.com/photos/91245453/medium.jpeg"
        },
        "taxon_changes_count": 1,
        "taxon_schemes_count": 2,
        "observations_count": 36,
        "flag_counts": {
          "resolved": 0,
          "unresolved": 0
        },
        "current_synonymous_taxon_ids": null,
        "atlas_id": null,
        "complete_species_count": null,
        "wikipedia_url": "http://en.wikipedia.org/wiki/Trimeresurus_kanburiensis",
        "complete_rank": "subspecies",
        "matched_term": "Trimeresurus kanburiensis",
        "iconic_taxon_name": "Reptilia",
        "preferred_common_name": "Kanburi Pit Viper",
        "conservation_status": {
          "id": 172415,
          "place_id": null,
          "source_id": null,
          "user_id": null,
          "authority": "IUCN Red List",
          "status": "en",
          "status_name": "endangered",
          "geoprivacy": "obscured",
          "iucn": 40
        }
      }
    ]
  }
}