{
  "timestamp": 1755986488313,
  "data": {
    "total_results": 1,
    "page": 1,
    "per_page": 10,
    "results": [
      {
        "id": 30947,
        "rank": "species",
        "rank_level": 10,
        "iconic_taxon_id": 26036,
        "ancestor_ids": [
          48460,
          1,
          2,
          355675,
          26036,
          26172,
          85553,
          30667,
          797576,
          30941,
          30947
        ],
        "is_active": true,
        "name": "Trimeresurus vogeli",
        "parent_id": 30941,
        "ancestry": "48460/1/2/355675/26036/26172/85553/30667/797576/30941",
        "extinct": false,
        "default_photo": {
          "id": 483784684,
          "license_code": null,
          "attribution": "(c) Natthaphat Chotjuckdikul, all rights reserved, uploaded by Natthaphat Chotjuckdikul",
          "url": "https://static.inaturalist.org/photos/483784684/square.jpg",
          "original_dimensions": {
            "height": 1364,
            "width": 2046
          },
          "flags": [],
          "attribution_name": "Natthaphat Chotjuckdikul",
          "square_url": "https://static.inaturalist.org/photos/483784684/square.jpg",
          "medium_url": "https://static.inaturalist.org/photos/483784684/medium.jpg"
        },
        "taxon_changes_count": 1,
        "taxon_schemes_count": 2,
        "observations_count": 430,
        "flag_counts": {
          "resolved": 0,
          "unresolved": 0
        },
        "current_synonymous_taxon_ids": null,
        "atlas_id": null,
        "complete_species_count": null,
        "wikipedia_url": "http://en.wikipedia.org/wiki/Trimeresurus_vogeli",
        "complete_rank": "subspecies",
        "matched_term": "Trimeresurus vogeli",
        "iconic_taxon_name": "Reptilia",
        "preferred_common_name": "Vogel’s Pit Viper"
      }
    ]
  }
}