{
  "timestamp": 1755945402317,
  "data": {
    "batchcomplete": "",
    "warnings": {
      "query": {
        "*": "Unrecognized value for parameter \"prop\": extmetadata"
      }
    },
    "query": {
      "pages": {
        "91613629": {
          "pageid": 91613629,
          "ns": 6,
          "title": "File:Endangered amphibians and reptiles of seven southwestern New Mexico counties (IA endangeredamphib6029belf).pdf",
          "imagerepository": "local",
          "imageinfo": [
            {
              "size": 32881220,
              "width": 633,
              "height": 831,
              "pagecount": 124,
              "url": "https://upload.wikimedia.org/wikipedia/commons/2/21/Endangered_amphibians_and_reptiles_of_seven_southwestern_New_Mexico_counties_%28IA_endangeredamphib6029belf%29.pdf",
              "descriptionurl": "https://commons.wikimedia.org/wiki/File:Endangered_amphibians_and_reptiles_of_seven_southwestern_New_Mexico_counties_(IA_endangeredamphib6029belf).pdf",
              "descriptionshorturl": "https://commons.wikimedia.org/w/index.php?curid=91613629"
            }
          ]
        }
      }
    }
  }
}